TOSLibrary/TOSLibrary.py
TOSLibrary/__init__.py
TOSLibrary/dynamic_library.py
tos/__init__.py
tos/settings.py
tos/statuses.py
tos/task_object_storage.py
tos/templates.py
tos/utils.py
tos/components/__init__.py
tos/components/creators.py
tos/components/finders.py
tos/components/query_helpers.py
tos/components/setters.py
tos/components/updaters.py
task_object_storage-1.4.0.dist-info/LICENSE
task_object_storage-1.4.0.dist-info/METADATA
task_object_storage-1.4.0.dist-info/WHEEL
task_object_storage-1.4.0.dist-info/top_level.txt
task_object_storage-1.4.0.dist-info/RECORD
