Metadata-Version: 2.2
Name: task-object-storage
Version: 1.4.0
Summary: Task Object Storage: Transaction management for Robot Framework RPA using MongoDB.
Author-email: SKALER / Siili Solutions Oyj <skaler-support@siili.com>
License: Copyright 2018-2025 Siili Solutions Oyj
Project-URL: Homepage, https://pypi.org/project/task-object-storage/
Classifier: Programming Language :: Python :: 3
Classifier: Operating System :: OS Independent
Classifier: Intended Audience :: Developers
Classifier: License :: OSI Approved :: Apache Software License
Requires-Python: >=3.9
License-File: LICENSE
Requires-Dist: dnspython
Requires-Dist: pymongo<5.0,>=4.0
Requires-Dist: robotframework>=3.1
Requires-Dist: wheel
